nekosfw/__init__.py
nekosfw/main.py
nekosfw-0.0.8.dist-info/LICENSE
nekosfw-0.0.8.dist-info/METADATA
nekosfw-0.0.8.dist-info/WHEEL
nekosfw-0.0.8.dist-info/top_level.txt
nekosfw-0.0.8.dist-info/RECORD
