Metadata-Version: 2.1
Name: nekosfw
Version: 0.0.8
Summary: Get SFW Neko Images
Home-page: https://github.com/Neko-SFW/nekosfw-py
Author: Crain69 (Chirayu Prasai)
Author-email: <chirayuprasai11@gmail.com>
License: UNKNOWN
Keywords: python,neko,sfw,rate limit,handler,images
Platform: UNKNOWN
Classifier: Development Status :: 1 - Planning
Classifier: Intended Audience :: Developers
Classifier: Programming Language :: Python :: 3
Classifier: Operating System :: Unix
Classifier: Operating System :: MacOS :: MacOS X
Classifier: Operating System :: Microsoft :: Windows
Requires-Dist: aiohttp
